gruut_lang_en/VERSION
gruut_lang_en/__init__.py
gruut_lang_en/lexicon.db
gruut_lang_en/espeak/lexicon.db
gruut_lang_en/espeak/g2p/model.crf
gruut_lang_en/g2p/model.crf
gruut_lang_en/pos/model.crf
babygruut_lang_en-2.0.2.dist-info/METADATA
babygruut_lang_en-2.0.2.dist-info/WHEEL
babygruut_lang_en-2.0.2.dist-info/top_level.txt
babygruut_lang_en-2.0.2.dist-info/RECORD
