Metadata-Version: 2.2
Name: babygruut_lang_en
Version: 2.0.2
Summary: English language files for gruut tokenizer/phonemizer
Home-page: https://github.com/bookbot-hive/babygruut
Classifier: Programming Language :: Python :: 3
Classifier: License :: OSI Approved :: MIT License
Dynamic: classifier
Dynamic: description
Dynamic: description-content-type
Dynamic: home-page
Dynamic: summary
